slack_installation_store/EncryptedFileInstallationStore.py
slack_installation_store/__init__.py
slack_oauth_store-0.0.4.dist-info/METADATA
slack_oauth_store-0.0.4.dist-info/WHEEL
slack_oauth_store-0.0.4.dist-info/top_level.txt
slack_oauth_store-0.0.4.dist-info/RECORD
