Metadata-Version: 2.1
Name: slack-oauth-store
Version: 0.0.4
Summary: Implementing Encrypted FileInstallationStore for Slack OAuth flow
Home-page: https://github.com/morningcloud/slack_installation_store
Author: Ghawady Ehmaid
Author-email: ghawady.ehmaid@gmail.com
License: UNKNOWN
Platform: UNKNOWN
Classifier: Programming Language :: Python :: 3
Classifier: License :: OSI Approved :: MIT License
Classifier: Operating System :: OS Independent
Requires-Python: >=3.6
Requires-Dist: slack-sdk (>=3.17.0)
Requires-Dist: pyAesCrypt (==6.0.0)
